{"titles":{"bp":"영국 의회","cp":"캐나다 의회","usp":"미국 의회","me":"메이스 확장 형식"},"notifications":{"title":"시간이 끝났습니다.","subtitle":"라운드 완료"},"settings":{"title":"설정","playMinutesRemainingSound":"남은 사운드를 재생하시겠습니까?","minuteRemainingRange":"이 분 범위의 경우"},"options":{"cp":{"title":"캐나다 의회","pmOption":"총리 : 6-4 또는 7-3분 라운드","coOption":"야당 지도자 : 한 번의 긴 라운드(전통) 또는 스플릿","split":"분할","trad":"전통","confirm":"확인"},"bp":{"title":"영국 의회","nbMinutes":"시간(분)"},"mace":{"title":"메이스 확장 형식","minutesMain":"주요 토론자 회의록","minutesSummary":"토론자 회의록 요약"}},"debateView":{"whoIsTalking":"누가 말하는 건가요?","poi":"질문 허용 ? (POI)","yes":"예","no":"아니요"},"accessibility":{"back":"이전 라운드로 돌아가기","start":"카운트다운 시작","pause":"일시 중지","skip":"이 라운드 건너뛰기"},"roles":{"cp":{"pm":"총리","co":"야당 지도자","mc":"왕실 장관","mo":"야당 회원"},"ap":{"pm":"하원 의장","co":"소수 민족 리더","mg":"다수 구성원","mo":"소수 구성원"},"bp":{"pm":"총리","co":"야당 대표","vpm":"부총리","cao":"야당 부대표","mg":"정부 구성원","mo":"야당 의원","wg":"정부 채찍","wo":"반대 채찍"},"me":{"fp":"첫 번째 명제","fo":"첫 번째 반대","sp":"두 번째 명제","so":"두 번째 반대","sup":"요약 제안","suo":"요약 반대"}},"welcome":{"header":"환영","title":"데바템프 애플리케이션에 오신 것을 환영합니다.","desc":"오른쪽 메뉴에서 토론 유형을 선택할 수 있습니다.","soundCreditTitle":"사운드 크레딧(프리사운드에서 제공)","alshred":"알슈레드 : 보호된 시간의 시작과 끝을 알리는 소리","tubbers":"튜버: 라운드 종료 시 박수 소리","cabled_mess":"케이블 혼잡: 남은 시간 동안 소리","MoonCube":"문큐브디자인: 마지막 초의 유예 시작 소리 및 알림 소리"}}